{
  "db_name": "SQLite",
  "query": "SELECT context_kind AS \"kind!\", context_ref AS \"reference\",\n                          COUNT(*) AS \"plays!: i64\", SUM(listen_ms) AS \"listen_ms!: i64\",\n                          MAX(context_name) AS \"name?: String\"\n                   FROM plays\n                   WHERE started_at >= ? AND started_at < ? AND context_kind = ? AND listen_ms >= ?\n                   GROUP BY context_ref ORDER BY 3 DESC, context_ref LIMIT ?",
  "describe": {
    "columns": [
      {
        "name": "kind!",
        "ordinal": 0,
        "type_info": "Text"
      },
      {
        "name": "reference",
        "ordinal": 1,
        "type_info": "Text"
      },
      {
        "name": "plays!: i64",
        "ordinal": 2,
        "type_info": "Null"
      },
      {
        "name": "listen_ms!: i64",
        "ordinal": 3,
        "type_info": "Null"
      },
      {
        "name": "name?: String",
        "ordinal": 4,
        "type_info": "Null"
      }
    ],
    "parameters": {
      "Right": 5
    },
    "nullable": [
      false,
      true,
      null,
      null,
      null
    ]
  },
  "hash": "8ca146df82fce8640f3dbcd2e212cd244be3ce58c5c735715be89fbcf49ef6db"
}
